FoFCatalogMatching.py
README.md
setup.py
FoFCatalogMatching.egg-info/PKG-INFO
FoFCatalogMatching.egg-info/SOURCES.txt
FoFCatalogMatching.egg-info/dependency_links.txt
FoFCatalogMatching.egg-info/requires.txt
FoFCatalogMatching.egg-info/top_level.txt